kestrel/__init__.py
kestrel/__main__.py
kestrel/config.py
kestrel/config.yaml
kestrel/exceptions.py
kestrel/session.py
kestrel/utils.py
kestrel/absinterface/__init__.py
kestrel/absinterface/manager.py
kestrel/analytics/__init__.py
kestrel/analytics/interface.py
kestrel/analytics/manager.py
kestrel/codegen/__init__.py
kestrel/codegen/commands.py
kestrel/codegen/data.py
kestrel/codegen/display.py
kestrel/codegen/prefetch.py
kestrel/codegen/queries.py
kestrel/codegen/relations.py
kestrel/codegen/summary.py
kestrel/datasource/__init__.py
kestrel/datasource/interface.py
kestrel/datasource/manager.py
kestrel/datasource/retstruct.py
kestrel/semantics/__init__.py
kestrel/semantics/completor.py
kestrel/semantics/processor.py
kestrel/semantics/reference.py
kestrel/symboltable/__init__.py
kestrel/symboltable/symtable.py
kestrel/symboltable/variable.py
kestrel/syntax/__init__.py
kestrel/syntax/ecgpattern.lark
kestrel/syntax/ecgpattern.py
kestrel/syntax/kestrel.lark
kestrel/syntax/parser.py
kestrel/syntax/reference.py
kestrel/syntax/utils.py
kestrel_analytics_docker/__init__.py
kestrel_analytics_docker/config.py
kestrel_analytics_docker/interface.py
kestrel_analytics_python/__init__.py
kestrel_analytics_python/config.py
kestrel_analytics_python/interface.py
kestrel_datasource_stixbundle/__init__.py
kestrel_datasource_stixbundle/interface.py
kestrel_datasource_stixshifter/__init__.py
kestrel_datasource_stixshifter/config.py
kestrel_datasource_stixshifter/connector.py
kestrel_datasource_stixshifter/diagnosis.py
kestrel_datasource_stixshifter/interface.py
kestrel_datasource_stixshifter/multiproc.py
kestrel_datasource_stixshifter/query.py
kestrel_datasource_stixshifter/worker/__init__.py
kestrel_datasource_stixshifter/worker/translator.py
kestrel_datasource_stixshifter/worker/transmitter.py
kestrel_datasource_stixshifter/worker/utils.py
kestrel_lang-1.7.6.data/scripts/ikestrel
kestrel_lang-1.7.6.data/scripts/kestrel
kestrel_lang-1.7.6.data/scripts/stix-shifter-diag
kestrel_lang-1.7.6.dist-info/AUTHORS.rst
kestrel_lang-1.7.6.dist-info/LICENSE.md
kestrel_lang-1.7.6.dist-info/METADATA
kestrel_lang-1.7.6.dist-info/WHEEL
kestrel_lang-1.7.6.dist-info/top_level.txt
kestrel_lang-1.7.6.dist-info/RECORD
