Metadata-Version: 2.1
Name: kestrel-lang
Version: 1.7.6
Summary: Kestrel Threat Hunting Language
Home-page: https://github.com/opencybersecurityalliance/kestrel-lang
License: Apache 2.0 License
Project-URL: Documentation, https://kestrel.readthedocs.io/
Keywords: domain specific language,cyber threat hunting,extended detection and response
Classifier: Topic :: Security
Classifier: Operating System :: OS Independent
Classifier: Development Status :: 4 - Beta
Classifier: License :: OSI Approved :: Apache Software License
Classifier: Programming Language :: Python :: 3
Classifier: Programming Language :: Python :: 3 :: Only
Requires-Python: >=3.8
License-File: LICENSE.md
License-File: AUTHORS.rst
Requires-Dist: typeguard >=4.1.5
Requires-Dist: pyyaml >=6.0.1
Requires-Dist: lxml >=4.9.3
Requires-Dist: lark >=1.1.7
Requires-Dist: pandas >=2.0.3
Requires-Dist: pyarrow >=13.0.0
Requires-Dist: docker >=6.1.3
Requires-Dist: requests >=2.31.0
Requires-Dist: nest-asyncio >=1.5.8
Requires-Dist: stix-shifter ==6.2.1
Requires-Dist: stix-shifter-utils ==6.2.1
Requires-Dist: firepit >=2.3.29
